[{"id":"ab778a51.68af28","type":"tab","label":"Flow 1","disabled":false,"info":""},{"id":"79a20bc5.d6fd94","type":"mqtt in","z":"ab778a51.68af28","name":"","topic":"Brew/test","qos":"2","datatype":"auto","broker":"ee3b2a73.10edc8","x":440,"y":40,"wires":[["e5c87b25.775d18","da703de3.456818"]]},{"id":"a1d68313.42355","type":"inject","z":"ab778a51.68af28","name":"","topic":"","payload":"Hello World","payloadType":"str","repeat":"","crontab":"","once":false,"onceDelay":0.1,"x":110,"y":40,"wires":[["8554f9c7.ab2778"]]},{"id":"8554f9c7.ab2778","type":"mqtt out","z":"ab778a51.68af28","name":"","topic":"Brew/test","qos":"2","retain":"","broker":"ee3b2a73.10edc8","x":300,"y":40,"wires":[]},{"id":"e5c87b25.775d18","type":"rpi-neopixels","z":"ab778a51.68af28","name":"","pixels":"50","bgnd":"10,10,10","fgnd":"200,200,200","wipe":"10","mode":"pixels","rgb":"rgb","brightness":"75","gamma":true,"x":670,"y":40,"wires":[]},{"id":"b43fe8ab.b074a8","type":"inject","z":"ab778a51.68af28","name":"Green","topic":"","payload":"255,0,0","payloadType":"str","repeat":"","crontab":"","once":false,"onceDelay":0.1,"x":650,"y":360,"wires":[["7350e94f.a86258"]]},{"id":"e73f93c8.9f0d48","type":"inject","z":"ab778a51.68af28","name":"Red","topic":"","payload":"0,255,0","payloadType":"str","repeat":"","crontab":"","once":false,"onceDelay":0.1,"x":650,"y":320,"wires":[["7350e94f.a86258"]]},{"id":"4b0428b9.84818","type":"inject","z":"ab778a51.68af28","name":"Blue","topic":"","payload":"0,0,255","payloadType":"str","repeat":"","crontab":"","once":false,"onceDelay":0.1,"x":650,"y":400,"wires":[["7350e94f.a86258"]]},{"id":"edcc6528.64d52","type":"inject","z":"ab778a51.68af28","name":"Clear (0,0,0)","topic":"","payload":"0,0,0","payloadType":"str","repeat":"","crontab":"","once":false,"onceDelay":0.1,"x":670,"y":280,"wires":[["7350e94f.a86258"]]},{"id":"4642dd3f.a300b4","type":"file in","z":"ab778a51.68af28","name":"","filename":"show.csv","format":"lines","chunk":false,"sendError":false,"encoding":"none","x":320,"y":460,"wires":[["f91378f8.5a72e"]]},{"id":"93441e8a.b263d","type":"inject","z":"ab778a51.68af28","name":"","topic":"","payload":"","payloadType":"date","repeat":"","crontab":"","once":false,"onceDelay":0.1,"x":140,"y":460,"wires":[["4642dd3f.a300b4"]]},{"id":"7350e94f.a86258","type":"link out","z":"ab778a51.68af28","name":"","links":["82411ec3.b0571"],"x":895,"y":380,"wires":[]},{"id":"82411ec3.b0571","type":"link in","z":"ab778a51.68af28","name":"","links":["7350e94f.a86258"],"x":495,"y":120,"wires":[["e5c87b25.775d18","da703de3.456818"]]},{"id":"c238835e.744d","type":"debug","z":"ab778a51.68af28","name":"","active":true,"tosidebar":true,"console":false,"tostatus":false,"complete":"false","x":830,"y":460,"wires":[]},{"id":"da703de3.456818","type":"debug","z":"ab778a51.68af28","name":"","active":false,"tosidebar":true,"console":false,"tostatus":false,"complete":"false","x":670,"y":120,"wires":[]},{"id":"f91378f8.5a72e","type":"delay","z":"ab778a51.68af28","name":"","pauseType":"delay","timeout":"1","timeoutUnits":"seconds","rate":"1","nbRateUnits":"1","rateUnits":"second","randomFirst":"1","randomLast":"5","randomUnits":"seconds","drop":false,"x":540,"y":460,"wires":[["7350e94f.a86258","c238835e.744d"]]},{"id":"ee3b2a73.10edc8","type":"mqtt-broker","z":"","name":"Rpi White","broker":"192.168.1.14","port":"1883","clientid":"","usetls":false,"compatmode":false,"keepalive":"60","cleansession":true,"birthTopic":"","birthQos":"0","birthRetain":"false","birthPayload":"","closeTopic":"","closeQos":"0","closeRetain":"false","closePayload":"","willTopic":"","willQos":"0","willRetain":"false","willPayload":""}]